yubaba/__init__.py
yubaba-0.1.0.dist-info/WHEEL
yubaba-0.1.0.dist-info/METADATA
yubaba-0.1.0.dist-info/RECORD
