Metadata-Version: 2.1
Name: yubaba
Version: 0.1.0
Summary: 
Author: edge-minato
Author-email: edge.minato@gmail.com
Requires-Python: >=3.8,<4.0
Classifier: Programming Language :: Python :: 3
Classifier: Programming Language :: Python :: 3.8
Classifier: Programming Language :: Python :: 3.9
Requires-Dist: single-source (>=0.2.0,<0.3.0)
